hash_dict/__init__.py
hash_dict/_key.py
hash_dict/comparer.py
hash_dict/hash_dict.py
hash_dict/hash_set.py
hash_dict-0.0.2.dist-info/LICENSE
hash_dict-0.0.2.dist-info/METADATA
hash_dict-0.0.2.dist-info/WHEEL
hash_dict-0.0.2.dist-info/top_level.txt
hash_dict-0.0.2.dist-info/RECORD
