Metadata-Version: 2.1
Name: hash-dict
Version: 0.0.2
Summary: UNKNOWN
Home-page: https://github.com/Cologler/hash-dict-python
Author: Cologler
Author-email: skyoflw@gmail.com
License: MIT License
Platform: UNKNOWN
Classifier: License :: OSI Approved :: MIT License
Classifier: Programming Language :: Python :: 3.6
Classifier: Programming Language :: Python :: 3.7
